{
    "conditions": {
        "num": {
            "=": {
                "conditionName": "Igual a"
            },
            "!=": {
                "conditionName": "Diferente de"
            },
            "!null": {
                "conditionName": "No esta vacio"
            },
            "<": {
                "conditionName": "Menor que"
            },
            "<=": {
                "conditionName": "Menor o igual que"
            },
            ">": {
                "conditionName": "Mayor que"
            },
            ">=": {
                "conditionName": "Mayor o igual que"
            },
            "null": {
                "conditionName": "Vacio"
            },
            "between": {
                "conditionName": "Entre"
            },
            "!between": {
                "conditionName": "No esta entre"
            }
        },
        "string": {
            "=": {
                "conditionName": "Igual a"
            },
            "!=": {
                "conditionName": "Diferente de"
            },
            "!null": {
                "conditionName": "No esta vacio"
            },
            "null": {
                "conditionName": "Vacio"
            },
            "starts": {
                "conditionName": "Empieza con"
            },
            "ends": {
                "conditionName": "Termina en"
            },
            "contains": {
                "conditionName": "Contiene"
            }
        }
    }
}